{"meta":{"type":"db","canSave":false,"canEdit":false,"canStar":true,"slug":"netapp-hci-vm-stats","expires":"0001-01-01T00:00:00Z","created":"2017-11-03T18:50:10Z","updated":"2018-01-19T21:08:33Z","updatedBy":"admin","createdBy":"admin","version":13},"dashboard":{"annotations":{"list":[{"builtIn":1,"datasource":"-- Grafana --","enable":true,"hide":true,"iconColor":"rgba(0, 211, 255, 1)","name":"Annotations \u0026 Alerts","type":"dashboard"}]},"description":"","editable":true,"gnetId":null,"graphTooltip":0,"hideControls":false,"id":7,"links":[],"rows":[{"collapse":false,"height":244,"panels":[{"aliasColors":{},"bars":false,"dashLength":10,"dashes":false,"datasource":null,"fill":1,"id":1,"legend":{"avg":false,"current":false,"max":false,"min":false,"show":true,"total":false,"values":false},"lines":true,"linewidth":1,"links":[],"nullPointMode":"null","percentage":false,"pointradius":5,"points":false,"renderer":"flot","seriesOverrides":[],"spaceLength":10,"span":6,"stack":false,"steppedLine":false,"targets":[{"refId":"A","target":"aliasByNode(scale(vsphere.$vcenter.virtualmachine.$VM.cpu.usage.maximum, 0.01), 3)"}],"thresholds":[],"timeFrom":null,"timeShift":null,"title":"$VM VM CPU Usage %","tooltip":{"shared":true,"sort":0,"value_type":"individual"},"type":"graph","xaxis":{"buckets":null,"mode":"time","name":null,"show":true,"values":[]},"yaxes":[{"format":"percent","label":null,"logBase":1,"max":null,"min":null,"show":true},{"format":"short","label":null,"logBase":1,"max":null,"min":null,"show":true}]},{"aliasColors":{},"bars":false,"dashLength":10,"dashes":false,"datasource":null,"description":"Math for CPU Ready % is (CPU Ready summation in ms)/(Chart Interval * 1000) * 100","fill":1,"id":2,"legend":{"avg":false,"current":false,"max":false,"min":false,"show":true,"total":false,"values":false},"lines":true,"linewidth":1,"links":[],"nullPointMode":"null","percentage":false,"pointradius":5,"points":false,"renderer":"flot","seriesOverrides":[],"spaceLength":10,"span":6,"stack":false,"steppedLine":false,"targets":[{"refId":"A","target":"aliasByNode(scale(scale(vsphere.$vcenter.virtualmachine.$VM.cpu.ready.summation, 0.0000166), 100), 3)"}],"thresholds":[],"timeFrom":null,"timeShift":null,"title":"$VM VM CPU Ready (per minute)","tooltip":{"shared":true,"sort":0,"value_type":"individual"},"type":"graph","xaxis":{"buckets":null,"mode":"time","name":null,"show":true,"values":[]},"yaxes":[{"format":"percent","label":null,"logBase":1,"max":null,"min":null,"show":true},{"format":"short","label":null,"logBase":1,"max":null,"min":null,"show":true}]}],"repeat":null,"repeatIteration":null,"repeatRowId":null,"showTitle":false,"title":"Dashboard Row","titleSize":"h6"},{"collapse":false,"height":250,"panels":[{"aliasColors":{},"bars":false,"dashLength":10,"dashes":false,"datasource":null,"fill":1,"id":3,"legend":{"avg":false,"current":false,"max":false,"min":false,"show":true,"total":false,"values":false},"lines":true,"linewidth":1,"links":[],"nullPointMode":"null","percentage":false,"pointradius":5,"points":false,"renderer":"flot","seriesOverrides":[],"spaceLength":10,"span":12,"stack":false,"steppedLine":false,"targets":[{"refId":"A","target":"aliasByNode(vsphere.$vcenter.virtualmachine.$VM.mem.active.maximum, 3)"}],"thresholds":[],"timeFrom":null,"timeShift":null,"title":"$VM - Active Memory","tooltip":{"shared":true,"sort":0,"value_type":"individual"},"type":"graph","xaxis":{"buckets":null,"mode":"time","name":null,"show":true,"values":[]},"yaxes":[{"format":"kbytes","label":null,"logBase":1,"max":null,"min":null,"show":true},{"format":"short","label":null,"logBase":1,"max":null,"min":null,"show":true}]}],"repeat":null,"repeatIteration":null,"repeatRowId":null,"showTitle":false,"title":"Dashboard Row","titleSize":"h6"},{"collapse":false,"height":250,"panels":[{"aliasColors":{},"bars":false,"dashLength":10,"dashes":false,"datasource":null,"fill":1,"id":4,"legend":{"avg":false,"current":false,"max":false,"min":false,"show":true,"total":false,"values":false},"lines":true,"linewidth":1,"links":[],"nullPointMode":"null","percentage":false,"pointradius":5,"points":false,"renderer":"flot","seriesOverrides":[],"spaceLength":10,"span":12,"stack":false,"steppedLine":false,"targets":[{"hide":true,"refId":"A","target":"aliasByNode(sumSeries(vsphere.$vcenter.virtualmachine.$VM.virtualdisk.numberreadaveraged.average.scsi0:0, vsphere.$vcenter.virtualmachine.$VM.virtualdisk.numberwriteaveraged.average.scsi0:0), 3)","textEditor":true},{"hide":false,"refId":"B","target":"aliasByNode(vsphere.$vcenter.virtualmachine.$VM.virtualdisk.numberreadaveraged.average.scsi0:0, 3)","textEditor":false},{"hide":false,"refId":"C","target":"aliasByNode(vsphere.$vcenter.virtualmachine.$VM.virtualdisk.numberwriteaveraged.average.scsi0:0, 3)","textEditor":false}],"thresholds":[],"timeFrom":null,"timeShift":null,"title":"$VM IOPS","tooltip":{"shared":true,"sort":0,"value_type":"individual"},"type":"graph","xaxis":{"buckets":null,"mode":"time","name":null,"show":true,"values":[]},"yaxes":[{"format":"short","label":null,"logBase":1,"max":null,"min":null,"show":true},{"format":"short","label":null,"logBase":1,"max":null,"min":null,"show":true}]}],"repeat":null,"repeatIteration":null,"repeatRowId":null,"showTitle":false,"title":"Dashboard Row","titleSize":"h6"}],"schemaVersion":14,"style":"dark","tags":["HCI"],"templating":{"list":[{"allValue":null,"current":{"text":"sfps-vcsa","value":"sfps-vcsa"},"datasource":"graphite-sfcollector","hide":0,"includeAll":true,"label":null,"multi":false,"name":"vcenter","options":[],"query":"vsphere.*","refresh":1,"regex":"","sort":0,"tagValuesQuery":"","tags":[],"tagsQuery":"","type":"query","useTags":false},{"allValue":null,"current":{"tags":[],"text":"All","value":"$__all"},"datasource":"graphite-sfcollector","hide":0,"includeAll":true,"label":null,"multi":false,"name":"VM","options":[{"selected":true,"text":"All","value":"$__all"},{"selected":false,"text":"hci-grafana01","value":"hci-grafana01"},{"selected":false,"text":"prime-addns01","value":"prime-addns01"},{"selected":false,"text":"sfps-jump01","value":"sfps-jump01"},{"selected":false,"text":"sfps-nabox01","value":"sfps-nabox01"},{"selected":false,"text":"sfps-pxe","value":"sfps-pxe"},{"selected":false,"text":"sfps-select01","value":"sfps-select01"},{"selected":false,"text":"sfps-vcsa","value":"sfps-vcsa"},{"selected":false,"text":"sfps-vsc71","value":"sfps-vsc71"},{"selected":false,"text":"solidfire-fdva-neon-patch1-10","value":"solidfire-fdva-neon-patch1-10"},{"selected":false,"text":"spfs-jump02","value":"spfs-jump02"}],"query":"vsphere.$vcenter.virtualmachine.*","refresh":0,"regex":"","sort":0,"tagValuesQuery":"","tags":[],"tagsQuery":"","type":"query","useTags":false}]},"time":{"from":"now-1h","to":"now"},"timepicker":{"refresh_intervals":["5s","10s","30s","1m","5m","15m","30m","1h","2h","1d"],"time_options":["5m","15m","1h","6h","12h","24h","2d","7d","30d"]},"timezone":"","title":"NetApp HCI - VM Stats","version":13}}